PyGRF/PyGRF.py
PyGRF/__init__.py
PyGRF-0.1.5.dist-info/LICENSE
PyGRF-0.1.5.dist-info/METADATA
PyGRF-0.1.5.dist-info/WHEEL
PyGRF-0.1.5.dist-info/top_level.txt
PyGRF-0.1.5.dist-info/RECORD
