Metadata-Version: 2.1
Name: PyGRF
Version: 0.1.5
Summary: PyGRF: An improved Python Geographical Random Forest model.
Home-page: https://github.com/geoai-lab/PyGRF
Author: Kai Sun, Ryan Zhenqi Zhou, Jiyeon Kim, and Yingjie Hu
Author-email: ksun4@buffalo.edu
License: MIT
Classifier: License :: OSI Approved :: MIT License
Classifier: Programming Language :: Python
Classifier: Programming Language :: Python :: 3
Classifier: Programming Language :: Python :: 3.6
Classifier: Programming Language :: Python :: Implementation :: CPython
Classifier: Programming Language :: Python :: Implementation :: PyPy
Requires-Python: >=3.8.0
License-File: LICENSE
